{"9018AE":"Shanghai Meridian Technologies, Co. Ltd.","903D6B":"Zicon Technology Corp.","904716":"RORZE CORPORATION","904CE5":"Hon Hai Precision Ind. Co.,Ltd.","906DC8":"DLG Automa\u00e7\u00e3o Industrial Ltda","907F61":"Chicony Electronics Co., Ltd.","90840D":"Apple, Inc.","90A7C1":"Pakedge Device and Software Inc.","90E6BA":"ASUSTek COMPUTER INC.","90FBA6":"Hon Hai Precision Ind. Co.,Ltd.","9055AE":"Ericsson, EAB/RWI/K","90A2DA":"GHEO SA","90F278":"Radius Gateway","9027E4":"Apple, Inc.","90513F":"Elettronica Santerno SpA","903D5A":"Shenzhen Wision Technology Holding Limited","90E0F0":"IEEE 1722a Working Group","905446":"TES ELECTRONIC SOLUTIONS","9088A2":"IONICS TECHNOLOGY ME LTDA","902155":"HTC Corporation","90903C":"TRISON TECHNOLOGY CORPORATION","90610C":"Fida International (S) Pte Ltd","902E87":"LabJack","90507B":"Advanced PANMOBIL Systems GmbH & Co. KG","9067B5":"Alcatel-Lucent","90A4DE":"WNC Corporation","90D7EB":"Texas Instruments","90D852":"Comtec Co., Ltd.","90D92C":"HUG-WITSCHI AG","90FB5B":"Avaya Inc","90004E":"Hon Hai Precision Ind. Co.,Ltd.","901900":"SCS SA","906EBB":"Hon Hai Precision Ind. Co.,Ltd.","909060":"RSI VIDEO TECHNOLOGIES","90B8D0":"Joyent, Inc.","90CF15":"Nokia Corporation","90EA60":"SPI Lasers Ltd","900917":"Far-sighted mobile","900D66":"Digimore Electronics Co., Ltd","905F8D":"modas GmbH","9067F3":"Alcatel Lucent","908D1D":"GH Technologies","90B97D":"Johnson Outdoors Marine Electronics d/b/a Minnkota","90E2BA":"Intel Corporate","90013B":"Sagemcom Broadband SAS","90342B":"Gatekeeper Systems, Inc.","90D11B":"Palomar Medical Technologies","9034FC":"Hon Hai Precision Ind. Co.,Ltd.","9002A9":"Zhejiang Dahua Technology Co., Ltd.","90A783":"JSW PACIFIC CORPORATION","90185E":"Apex Tool Group GmbH & Co OHG","9092B4":"Diehl BGT Defence GmbH & Co. KG","903CAE":"Yunnan KSEC Digital Technology Co.,Ltd.","905682":"Lenbrook Industries Limited","90D74F":"Bookeen","908FCF":"UNO System Co., Ltd","903AA0":"Nokia","90F652":"TP-LINK TECHNOLOGIES CO.,LTD.","9003B7":"PARROT SA","902B34":"GIGA-BYTE TECHNOLOGY CO.,LTD.","90C115":"Sony Corporation","900A3A":"PSG Plastic Service GmbH","90B134":"Commscope","90F4C1":"Rand McNally","901B0E":"Fujitsu Technology Solutions GmbH","90AC3F":"BrightSign LLC","90CF7D":"Qingdao Hisense Communications Co.,Ltd.","90F72F":"Phillips Machine & Welding Co., Inc.","9094E4":"D-Link International","901EDD":"GREAT COMPUTER CORPORATION","907025":"Garea Microsys Co.,Ltd.","909DE0":"Newland Design + Assoc. Inc.","9059AF":"Texas Instruments","90B11C":"Dell Inc.","90CF6F":"Dlogixs Co Ltd","900DCB":"Commscope","90187C":"SAMSUNG ELECTRO MECHANICS CO., LTD.","9038DF":"Changzhou Tiannengbo System Co. Ltd.","901D27":"zte corporation","905F2E":"TCT mobile ltd","908260":"IEEE 1904.1 Working Group","90CC24":"Synaptics, Inc","90FF79":"Metro Ethernet Forum","90DA4E":"AVANU","905692":"Autotalks Ltd.","907AF1":"Wally","9046B7":"Vadaro Pte Ltd","903EAB":"Commscope","9049FA":"Intel Corporate","907A0A":"Gebr. Bode GmbH & Co KG","907A28":"Beijing Morncloud Information And Technology Co. Ltd.","907240":"Apple, Inc.","90B21F":"Apple, Inc.","906717":"Alphion India Private Limited","907990":"Benchmark Electronics Romania SRL","909916":"ELVEES NeoTek OJSC","909F43":"Accutron Instruments Inc.","90028A":"Shenzhen Shidean Legrand Electronic Products Co.,Ltd","901ACA":"Commscope","902083":"General Engine Management Systems Ltd.","90356E":"Vodafone Omnitel N.V.","908C44":"H.K ZONGMU TECHNOLOGY CO., LTD.","908F93":"MakerBot Industries","90F3B7":"Kirisun Communications Co., Ltd.","9031CD":"Onyx Healthcare Inc.","904E2B":"HUAWEI TECHNOLOGIES CO.,LTD","90837A":"General Electric Water & Process Technologies","90B931":"Apple, Inc.","90DFB7":"s.m.s smart microwave sensors GmbH","909864":"Impex-Sat GmbH&amp;Co KG","90DB46":"E-LEAD ELECTRONIC CO., LTD","90F1AA":"Samsung Electronics Co.,Ltd","90F1B0":"Hangzhou Anheng Info&Tech CO.,LTD","90AE1B":"TP-LINK TECHNOLOGIES CO.,LTD.","907EBA":"UTEK TECHNOLOGY (SHENZHEN) CO.,LTD","90489A":"Hon Hai Precision Ind. Co.,Ltd.","908C63":"GZ Weedong Networks Technology Co. , Ltd","90C792":"Commscope","90B686":"Murata Manufacturing Co., Ltd.","90DA6A":"FOCUS H&S Co., Ltd.","90179B":"Nanomegas","90203A":"BYD Precision Manufacture Co.,Ltd","902181":"Shanghai Huaqin Telecom Technology Co.,Ltd","909F33":"EFM Networks","90EF68":"Zyxel Communications Corporation","90FD61":"Apple, Inc.","9017AC":"HUAWEI TECHNOLOGIES CO.,LTD","902CC7":"C-MAX Asia Limited","9068C3":"Motorola Mobility LLC, a Lenovo Company","908C09":"Total Phase","900CB4":"Alinket Electronic Technology Co., Ltd","908D6C":"Apple, Inc.","904506":"Tokyo Boeki Medisys Inc.","90C35F":"Nanjing Jiahao Technology Co., Ltd.","90E7C4":"HTC Corporation","906F18":"Private","90A210":"United Telecoms Ltd","902106":"SKY UK LIMITED","906CAC":"Fortinet, Inc.","90C682":"IEEE Registration Authority","907282":"Sagemcom Broadband SAS","90DFFB":"HOMERIDER SYSTEMS","9023EC":"Availink, Inc.","90D8F3":"zte corporation","900A39":"Wiio, Inc.","9097D5":"Espressif Inc.","9000DB":"Samsung Electronics Co.,Ltd","90C99B":"Tesorion Nederland B.V.","906FA9":"NANJING PUTIAN TELECOMMUNICATIONS TECHNOLOGY CO.,LTD.","902E1C":"Intel Corporate","90CDB6":"Hon Hai Precision Ind. Co.,Ltd.","9060F1":"Apple, Inc.","90671C":"HUAWEI TECHNOLOGIES CO.,LTD","903C92":"Apple, Inc.","908D78":"D-Link International","900BC1":"Sprocomm Technologies CO.,Ltd","90A62F":"NAVER","9046A2":"Tedipay UK Ltd","900325":"HUAWEI TECHNOLOGIES CO.,LTD","90C7D8":"zte corporation","90C6822":"ekey biometric systems gmbh","90C682E":"Shanghai HuRong Communication Technology Development Co., Ltd.","90C6829":"ACT","90C682F":"Private","90C682B":"Lachmann & Rink GmbH","90C6825":"S.A.E.T. S.R.L.","90C6827":"Cinet Inc","90C6820":"Shenzhen Lencotion Technology Co.,Ltd","90C682D":"PowerShield Limited","90C6828":"Teletek Electronics","90C6823":"Innovative Electronic Technology","90C682A":"Beijing Acorn Networks Corporation","90C6826":"Nanjing Jiexi Technologies Co., Ltd.","90C6821":"Shenzhen Photon Broadband Technology CO., LTD","90C6824":"Neone, Inc.","90C682C":"Li Seng Technology Ltd.","903809":"Ericsson AB","904D4A":"Sagemcom Broadband SAS","90C1C6":"Apple, Inc.","90B0ED":"Apple, Inc.","90EED9":"UNIVERSAL DE DESARROLLOS ELECTR\u00d3NICOS, SA","90F052":"MEIZU Technology Co., Ltd.","903AE6":"PARROT SA","90A46A":"SISNET CO., LTD","90842B":"LEGO System A/S","905C44":"Compal Broadband Networks, Inc.","90D7BE":"Wavelab Global Inc.","901711":"Hagenuk Marinekommunikation GmbH","90505A":"unGlue, Inc","908674":"Sichuan Tianyi Comheart Telecom Co.,LTD","900628":"Samsung Electronics Co.,Ltd","900E83":"Monico Monitoring, Inc.","90F305":"HUMAX Co., Ltd.","9097F3":"Samsung Electronics Co.,Ltd","907065":"Texas Instruments","90EC50":"C.O.B.O. SPA","9061AE":"Intel Corporate","900A1A":"Taicang T&W Electronics","90A365":"HMD Global Oy","909D7D":"Commscope","9050CA":"Hitron Technologies. Inc","90ADF7":"vivo Mobile Communication Co., Ltd.","90B1E0":"Beijing Nebula Link Technology Co., Ltd","90324B":"Hon Hai Precision Ind. Co.,Ltd.","903DBD":"SECURE METERS LIMITED","904E91":"IEEE Registration Authority","90FD9F":"Silicon Laboratories","904E916":"Nuwa Robotics (HK) Limited Taiwan Branch","904E910":"Spirtech","904E915":"ENGINKO SRL","904E91E":"Shenzhen Cloudynamo Internet Technologies Co.,LTD.","904E917":"IBM","904E91D":"SKODA ELECTRIC a.s.","904E918":"CommandScape, Inc.","904E911":"Apollo Video Technology","904E91B":"Shanghai JaWay Information Technology Co., Ltd.","904E912":"North Pole Engineering, Inc.","904E914":"Wrtnode technology Inc.","904E91C":"Showtacle s.r.o.","904E913":"Great Talent Technology Limited","904E91A":"Kaertech Limited","904E919":"CUTTER Systems spol. s r.o.","90848B":"HDR10+ Technologies, LLC","903A72":"Ruckus Wireless","900372":"Longnan Junya Digital Technology Co. Ltd.","909497":"HUAWEI TECHNOLOGIES CO.,LTD","90834B":"BEIJING YUNYI TIMES TECHNOLOGY CO,.LTD","907910":"Integrated Device Technology (Malaysia) Sdn. Bhd.","90DD5D":"Apple, Inc.","903D68":"G-Printec, Inc.","90A137":"Beijing Splendidtel Communication Technology Co,. Ltd","904C81":"Hewlett Packard Enterprise","902BD2":"HUAWEI TECHNOLOGIES CO.,LTD","900EB3":"Shenzhen Amediatech Technology Co., Ltd.","90E17B":"Apple, Inc.","90E710":"New H3C Technologies Co., Ltd","90C54A":"vivo Mobile Communication Co., Ltd.","90633B":"Samsung Electronics Co.,Ltd","90E202":"Texas Instruments","90869B":"zte corporation","907E30":"LARS","900218":"SKY UK LIMITED","90940A":"Analog Devices, Inc","905851":"Vantiva USA LLC","907A58":"Zegna-Daidong Limited","90895F":"WEIFANG GOERTEK ELECTRONICS CO.,LTD","906D05":"BXB ELECTRONICS CO., LTD","90F891":"Kaon Group Co., Ltd.","9020C2":"Hewlett Packard Enterprise","904DC3":"Flonidan A/S","907841":"Intel Corporate","905C34":"Sirius Electronic Systems Srl","90735A":"Motorola Mobility LLC, a Lenovo Company","9078B2":"Xiaomi Communications Co Ltd","90BDE6":"Quectel Wireless Solutions Co.,Ltd.","90272B":"Algorab S.r.l.","901234":"Shenzhen YOUHUA Technology Co., Ltd","9017C8":"HUAWEI TECHNOLOGIES CO.,LTD","909A77":"Texas Instruments","90473C":"China Mobile Group Device Co.,Ltd.","90B832":"Extreme Networks Headquarters","901A4F":"EM Microelectronic","90B8E0":"SHENZHEN YANRAY TECHNOLOGY CO.,LTD","90AFD1":"netKTI Co., Ltd","9013DA":"Athom B.V.","90812A":"Apple, Inc.","90FD73":"zte corporation","900CC8":"Google, Inc.","9055DE":"Fiberhome Telecommunication Technologies Co.,LTD","90B144":"Samsung Electronics Co.,Ltd","90A25B":"Apple, Inc.","9043E2":"Cornami, Inc","90E2FCD":"Beijing Lanxum Computer Technology CO.,LTD.","90E2FC":"IEEE Registration Authority","90E2FC0":"PEA (DBT-Technology)","90E2FC9":"Huddly AS","90E2FC4":"Dongguan Kangyong electronics technology Co. Ltd","90E2FC2":"ShenZhen Temwey Innovation Technology Co.,Ltd.","90E2FC8":"bitsensing Inc.","90E2FCC":"Stanley Security","90E2FCA":"Power Engineering & Manufacturing, Inc.","90E2FC6":"Sindoh Techno Co., Ltd.","90E2FC3":"Shenzhen Hisource Technology Development CO.,Ltd.","90E2FC5":"TOTALONE TECHNOLOGY CO., LTD.","90E2FC1":"Yite technology","90E2FCB":"Shenzhen Dingsheng Intelligent Technology Co., Ltd","90E2FCE":"DevCom spol. s r.o.","90E2FC7":"Fair Winds Digital srl","90749D":"IRay Technology Co., Ltd.","909C4A":"Apple, Inc.","908C43":"Apple, Inc.","90ADFC":"Telechips, Inc.","90EC77":"silicom","905D7C":"New H3C Technologies Co., Ltd","9056FC":"TECNO MOBILE LIMITED","900A84":"Mellanox Technologies, Inc.","90173F":"HUAWEI TECHNOLOGIES CO.,LTD","909838":"Huawei Device Co., Ltd.","90EEC7":"Samsung Electronics Co.,Ltd","9016BA":"HUAWEI TECHNOLOGIES CO.,LTD","9077EE":"Cisco Systems, Inc","903FEA":"HUAWEI TECHNOLOGIES CO.,LTD","90769F":"SHENZHEN MERCURY COMMUNICATION TECHNOLOGIES CO.,LTD.","909164":"ChongQing Lavid Technology Co., Ltd.","90A935":"JWEntertainment","90F644":"Huawei Device Co., Ltd.","9012A1":"We Corporation Inc.","90AAC3":"Hitron Technologies. Inc","90CCDF":"Intel Corporate","90A5AF":"HUAWEI TECHNOLOGIES CO.,LTD","908158":"Apple, Inc.","909A4A":"TP-LINK TECHNOLOGIES CO.,LTD.","90808F":"Huawei Device Co., Ltd.","90DE80":"Shenzhen Century Xinyang Technology Co., Ltd","90B4DD":"ZPT R&D","90FFD6":"Honor Device Co., Ltd.","900F0C":"CLOUD NETWORK TECHNOLOGY SINGAPORE PTE. LTD.","903CB3":"Edgecore Networks Corporation","90027A":"Shenzhen Sworix Techonlogy Co., Ltd","9023B4":"New H3C Technologies Co., Ltd","90C119":"Nokia","90A822":"Amazon Technologies Inc.","90B67A":"Shenzhen Skyworth Digital  Technology  CO., Ltd","90F9B7":"HUAWEI TECHNOLOGIES CO.,LTD","9096F3":"BUFFALO.INC","908060":"Nilfisk A/S","906976":"Withrobot Inc.","902E16":"LCFC(Hefei) Electronics Technology co., ltd","90B57F":"Shenzhen iComm Semiconductor CO.,LTD","90593C":"AZ-TECHNOLOGY SDN BHD","90F157":"Garmin International","90E868":"AzureWave Technology Inc.","906A94":"hangzhou huacheng network technology co., ltd","9009D0":"Synology Incorporated","908175":"Samsung Electronics Co.,Ltd","90B622":"Samsung Electronics Co.,Ltd","908D6E":"Dell Inc.","9035EA":"Silicon Laboratories","90F3B8":"China Mobile Group Device Co.,Ltd.","90380C":"Espressif Inc.","90EB48":"Shanghai XinMiaoLink Technology Co., Ltd","903E7F":"Fiberhome Telecommunication Technologies Co.,LTD","902759":"Nanjing Jiahao Technology Co., Ltd.","9075BC":"Nokia Shanghai Bell Co., Ltd.","901195":"Amazon Technologies Inc.","90F260":"Shenzhen Honesty Electronics Co.,Ltd.","90DF7D":"Realme Chongqing Mobile Telecommunications Corp.,Ltd.","90F7B2":"New H3C Technologies Co., Ltd","9079CF":"zte corporation","90486C":"Ring LLC","90935A":"Commscope","90D473":"vivo Mobile Communication Co., Ltd.","902CFB":"CanTops Co,.Ltd.","904992":"YSTen Technology Co.,Ltd","905E44":"HUAWEI TECHNOLOGIES CO.,LTD","90CD1F":"Quectel Wireless Solutions Co.,Ltd.","90235B":"Amazon Technologies Inc.","90F970":"HUAWEI TECHNOLOGIES CO.,LTD","906AEB":"Microsoft Corporation","906560":"EM Microelectronic","900A62":"Inventus Power Eletronica do Brasil LTDA","9025F2":"HUAWEI TECHNOLOGIES CO.,LTD","90CAFA":"Google, Inc.","909877":"Vestel Elektronik San ve Tic. A.S.","906584":"Intel Corporate","9009DF":"Intel Corporate","900117":"HUAWEI TECHNOLOGIES CO.,LTD","90DAF9":"Siemens Rail Automation SAU","902778":"Open Infrastructure","90F82E":"Amazon Technologies Inc.","907BC6":"Texas Instruments","904846":"Texas Instruments","90395E":"Silicon Laboratories","90A6BF":"Quectel Wireless Solutions Co.,Ltd.","90AB96":"Silicon Laboratories","90CEB8":"Texas Instruments","90314B":"AltoBeam Inc.","909B6F":"Apple, Inc.","90ECEA":"Apple, Inc.","9052BF":"Sichuan Tianyi Comheart Telecom Co.,LTD","90D689":"Huahao Fangzhou Technology Co.,Ltd","90E95E":"Cisco Systems, Inc","90CC7A":"Huawei Device Co., Ltd.","907E43":"zte corporation","902AEE":"Xiaomi Communications Co Ltd","90A7BF":"EM Microelectronic","903C1D":"HISENSE VISUAL TECHNOLOGY CO.,LTD","9006F2":"Texas Instruments","90EB50":"Cisco Systems, Inc","906D62":"Cambium Networks Limited","908855":"Cisco Systems, Inc","90395F":"Amazon Technologies Inc.","90F4214":"Sansap Technology Pvt. Ltd.","90F421":"IEEE Registration Authority","90F421C":"ACOBA","90F4212":"Catvision Ltd.","90F4215":"DESKO GmbH","90F4210":"Gemstone Lights","90F421B":"Jiangsu MSInfo Technology Co.,Ltd.","90F4213":"Sinpeng(Guangzhou)Technology Co.,Ltd","90F421A":"Proqualit Telecom LTDA","90F421D":"Taichitel Technology Shanghai Co.,Ltd.","90F4217":"Senstar Corporation","90F4219":"Twunicom Life Tech. Co., Ltd.","90F4211":"BeEnergy SG GmbH","905607":"Sichuan\u00a0AI-Link\u00a0Technology\u00a0Co.,\u00a0Ltd.","9070D3":"Fiberhome Telecommunication Technologies Co.,LTD","905A08":"Super Micro Computer, Inc.","90F4218":"Mi-Jack Products","90ECE3":"Nokia","90F4216":"Wuxi Sunning Smart Devices Co.,Ltd","90F421E":"Velan Studios Inc.","90CFBE":"Enablers Solucoes e Consultoria em Dispositivos","90D092":"HUMAX Co., Ltd.","90E468":"Guangzhou Shiyuan Electronic Technology Company Limited","90837E":"Fiberhome Telecommunication Technologies Co.,LTD","9064AD":"HUAWEI TECHNOLOGIES CO.,LTD","900E9E":"Shenzhen SuperElectron Technology Co.,Ltd.","90C710":"zte corporation","906C4B":"Advance Security Electronics","902D77":"Edgecore Americas Networking Corporation","90A1BA":"PNetworks Electronics Information","9075DE":"Zebra Technologies Inc.","902C09":"Apple, Inc.","90A57D":"Huawei Device Co., Ltd.","909E24":"ekey biometric systems gmbh","904528":"Nintendo Co.,Ltd","90A9F7":"IEEE Registration Authority","90B685":"WEIFANG GOERTEK ELECTRONICS CO.,LTD","90A9F79":"Zekler Safety AB","90A9F78":"BAODING FORLINX EMBEDDEDTECHNOLOGY CO., LTD","90A9F73":"Suzhou Etag-Technology Corporation","90A9F75":"Shenzhen DOOGEE Hengtong Technology CO.,LTD","90A9F74":"LAB-EL ELEKTRONIKA LABORATORYJNA","90A9F7E":"The Engineerix Group","90A9F7C":"SkyLine Limited Technologies Co., Ltd","90A9F72":"Suzhou Lingchen Acquisition Computer","90A9F7D":"Shanghai Jiehezhi Technology Co., Ltd.","90A9F70":"Versta","90A9F71":"Shenzhen Chainway Information Technology Co., Ltd","90A9F76":"Shenzhen Eevin Technology Co.,Ltd","90A9F77":"GUANGDONG KERUIDE ELECTRICAL TECHNOLOGY CO., LTD.","90A9F7A":"Chi Geng Technology Co., Ltd","90A9F7B":"Kranze Technology Solutions, Inc.","90D432":"zte corporation","908938":"Hefei Linkin Technology Co., Ltd.","90623F":"Apple, Inc.","90A0BE":"Cannice","90F721":"IndiNatus (IndiNatus India Private Limited)","90212E":"Apption Labs Ltd","900371":"Quectel Wireless Solutions Co.,Ltd.","9015646":"final Inc.","901564B":"Shanghai AMP&MOONS'Automation Co.,Ltd.","901564":"IEEE Registration Authority","9015642":"PIN GENIE, INC.DBA LOCKLY","9015640":"Fengzhushou Co., Ltd.","9015647":"Hangzhou System Technology Co.,Ltd","9015648":"Heliogen","9015645":"Relectrify Pty Ltd","901564C":"LINAK A/S","9015643":"Clinton Electronics Corporation","9015649":"Annapurna labs","901564D":"Jiangsu Kangjie Data Co., Ltd.","9015644":"Kontakt Micro-Location Sp z o.o.","901564E":"Guiyag Electrlcal Control Equipment Co.,Ltd","901564A":"Bunka Shutter Co., Ltd.","90D3CF":"ASKEY COMPUTER CORP","90CBA3":"TECNO MOBILE LIMITED","909F22":"Zyxel Communications Corporation","901506":"Espressif Inc.","9054B7":"Eltex Enterprise LTD","90B790":"Apple, Inc.","905F7A":"Apple, Inc.","90FB5D":"Beijing Xiaomi Mobile Software Co., Ltd","9028F6":"Wuhan Yangtze Optical Technology CO.,Ltd.","90032E":"Taicang T&W Electronics","904CC5":"Apple, Inc.","90A196":"Private","9070BF":"Mimosa Networks","9082C3":"Quanta Computer Inc.","909DAC":"Infinix mobility limited","905671":"Cisco Systems, Inc","90E4B0":"SHARP Corporation","90EF4A":"Dongguan Liesheng Electronic Co., Ltd.","9088A9":"IEEE Registration Authority","9088A92":"\u5408\u80a5\u4e7e\u76fe\u667a\u80fd\u79d1\u6280\u6709\u9650\u516c\u53f8","9088A96":"Skysolid Information Security Systems(Shenzhen) Co., Ltd","9088A95":"Shortcut Labs AB","9088A94":"asmote ltd.","9088A90":"shenzhen zovoton electronic co.,ltd","9088A9D":"REMOWIRELESS COMMUNICATION INTERNATIONAL CO.,LIMITED","9088A9A":"Yi Tunnel(beijing) Technology Co.,Ltd","9088A9B":"UXV Technologies ApS","9088A98":"Samway Electronic SRL","90BFD9":"Smart Innovation LLC","9088A97":"Wingtech Mobile Communications Co.,Ltd.","9088A9C":"Rikom Technologies Sdn Bhd","9088A93":"Hangzhou Hollysys Automation Co., Ltd","9088A99":"Nanjing Boswell Industrial Communication Technology Co., Ltd","9088A91":"Akarui Networks Pvt Ltd","9088A9E":"TeeJet Technologies","90CDE8":"Apple, Inc.","909507":"HUAWEI TECHNOLOGIES CO.,LTD","903CDA":"Fiberhome Telecommunication Technologies Co.,LTD","901057":"Intel Corporate","90E643":"Tesla,Inc.","90F964":"Rawasi Co","90B942":"zte corporation","90E5B1":"Espressif Inc.","90D20B":"Nokia Shanghai Bell Co., Ltd.","90742E":"New H3C Technologies Co., Ltd","904748":"Sony Interactive Entertainment Inc.","90AC6D":"Apple, Inc.","90E317":"Mellanox Technologies, Inc.","903FC3":"Huawei Device Co., Ltd.","9014AF":"Cambium Networks Limited","904C02":"vivo Mobile Communication Co., Ltd.","90F005":"Xi'an Molead Technology Co., Ltd","902962":"Linkpower Microelectronics Co., Ltd.","907069":"Espressif Inc.","90FEE2":"ISIF","903F86":"New H3C Technologies Co., Ltd","90B021":"Intel Corporate","9041B2":"Ubiquiti Inc","90FB93":"Renesas Design US Inc.","903196":"SHENZHEN IP-COM NETWORKS CO.,LTD.","901C9E":"Alcatel-Lucent Enterprise","9035A2":"Apple, Inc.","907ABE":"GSD VIET NAM TECHNOLOGY COMPANY LIMITED","90AF59":"Choice IT Global LLC","90C952":"Durin, Inc","906FA7":"Funshion Online Technologies Co.,Ltd","901F09":"Silicon Laboratories","90F861":"u-blox AG","9074AE":"AzureWave Technology Inc.","907ADA":"CHINA DRAGON TECHNOLOGY LIMITED","9051F8":"Hewlett Packard Enterprise","908A80":"Cisco Systems, Inc","90B9F9":"Motorola Mobility LLC, a Lenovo Company","9020D7":"Microsoft Corporation"}